{
    "GRUPO PENINSULA SOLUCOES AGRICOLAS LTDA": {
        "empresa_id": "829",
        "identificação": "51.832.074/0001-25",
        "fgts_total": 732.8,
        "inss_total": 1002.55,
        "competencia": "11",
        "emissao": "03/12/2024"
    },
    "NAURO VELHO SESSIM": {
        "empresa_id": "508",
        "identificação": "11.818.255/0001-82",
        "fgts_total": 152.09,
        "inss_total": 1245.42,
        "competencia": "11",
        "emissao": "03/12/2024"
    },
    "PAULO MARQUES SOUZA DA ROSA": {
        "empresa_id": "627",
        "identificação": "553.878.290/001-92",
        "fgts_total": 174.24,
        "inss_total": 183.54,
        "competencia": "11",
        "emissao": "03/12/2024"
    },
    "PEDRO AZEVEDO GADEA": {
        "empresa_id": "799",
        "identificação": "007.709.350/001-69",
        "fgts_total": 213.13,
        "inss_total": 362.43,
        "competencia": "11",
        "emissao": "03/12/2024"
    },
    "RAFAEL VELHO SILVEIRA E OUTRO": {
        "empresa_id": "673",
        "identificação": "012.654.450/001-78",
        "fgts_total": 585.98,
        "inss_total": 2473.7799999999997,
        "competencia": "11",
        "emissao": "03/12/2024"
    },
    "RODRIGO DE CAMPOS PEREIRA": {
        "empresa_id": "164",
        "identificação": "06.971.699/0001-13",
        "fgts_total": 274.44,
        "inss_total": 434.68,
        "competencia": "11",
        "emissao": "03/12/2024"
    },
    "SEMENTINHA COMIDA COM AFETO LTDA": {
        "empresa_id": "828",
        "identificação": "51.784.249/0001-76",
        "fgts_total": 498.86,
        "inss_total": 1047.67,
        "competencia": "11",
        "emissao": "03/12/2024"
    },
    "TRANS NAFH TRANSPORTES LTDA": {
        "empresa_id": "616",
        "identificação": "15.771.867/0001-18",
        "fgts_total": 1044.31,
        "inss_total": 11097.29,
        "competencia": "11",
        "emissao": "03/12/2024"
    },
    "VERA R. DA SILVA": {
        "empresa_id": "675",
        "identificação": "18.963.545/0001-69",
        "fgts_total": 225.92,
        "inss_total": 211.8,
        "competencia": "11",
        "emissao": "03/12/2024"
    }
}